pdftools/pdfposter/__init__.py
pdftools/pdfposter/cmd.py
pdftools.pdfposter-0.9.dist-info/LICENSE-GPLv3.txt
pdftools.pdfposter-0.9.dist-info/METADATA
pdftools.pdfposter-0.9.dist-info/WHEEL
pdftools.pdfposter-0.9.dist-info/entry_points.txt
pdftools.pdfposter-0.9.dist-info/top_level.txt
pdftools.pdfposter-0.9.dist-info/zip-safe
pdftools.pdfposter-0.9.dist-info/RECORD
