Metadata-Version: 2.1
Name: pdftools.pdfposter
Version: 0.9
Summary: Scale and tile PDF images/pages to print on multiple pages.
Home-page: https://pdfposter.readthedocs.io/
Download-URL: https://pypi.org/project/pdftools.pdfposter/
Author: Hartmut Goebel
Author-email: h.goebel@crazy-compilers.com
License: GNU General Public License v3 or later (GPLv3+)
Keywords: pdf,poster
Classifier: Development Status :: 5 - Production/Stable
Classifier: Environment :: Console
Classifier: Intended Audience :: Developers
Classifier: Intended Audience :: End Users/Desktop
Classifier: Intended Audience :: System Administrators
Classifier: License :: OSI Approved :: GNU General Public License v3 or later (GPLv3+)
Classifier: Natural Language :: English
Classifier: Operating System :: OS Independent
Classifier: Programming Language :: Python
Classifier: Topic :: Printing
Classifier: Topic :: Utilities
License-File: LICENSE-GPLv3.txt
Requires-Dist: setuptools
Requires-Dist: pdfposter >=0.9
